virtualitics/__init__.py
virtualitics/api.py
virtualitics/assets/ColorWheel_512.png
virtualitics/assets/Inter-Regular.ttf
virtualitics/assets/Shape_Crescent_512.png
virtualitics/assets/Shape_Cross_512.png
virtualitics/assets/Shape_Cube_512.png
virtualitics/assets/Shape_MissingValue_512.png
virtualitics/assets/Shape_Plus_512.png
virtualitics/assets/Shape_Pyramid_512.png
virtualitics/assets/Shape_Sphere_512.png
virtualitics/assets/__init__.py
virtualitics/assets/shapes.png
virtualitics/encryption.py
virtualitics/exceptions.py
virtualitics/explore/__init__.py
virtualitics/explore/workflow.py
virtualitics/explore/workflow_constants.py
virtualitics/explore/workflow_entry.py
virtualitics/legend_builder.py
virtualitics/pkcs7.py
virtualitics/task_response_handlers.py
virtualitics/utils.py
virtualitics/vip_annotation.py
virtualitics/vip_dashboard.py
virtualitics/vip_object.py
virtualitics/vip_plot.py
virtualitics/vip_result.py
pyvip-1.26.0.dist-info/LICENSE
pyvip-1.26.0.dist-info/METADATA
pyvip-1.26.0.dist-info/WHEEL
pyvip-1.26.0.dist-info/RECORD
