Metadata-Version: 2.3
Name: pyvip
Version: 1.26.0
Summary: Python API for Virtualitics Explore
License: MIT
Author: Virtualitics Engineering
Author-email: dev@virtualitics.com
Requires-Python: >=3.8,<4.0
Classifier: License :: OSI Approved :: MIT License
Classifier: Operating System :: MacOS :: MacOS X
Classifier: Operating System :: Microsoft :: Windows :: Windows 10
Classifier: Operating System :: POSIX
Classifier: Programming Language :: Python :: 3
Classifier: Programming Language :: Python :: 3.8
Classifier: Programming Language :: Python :: 3.9
Classifier: Programming Language :: Python :: 3.10
Classifier: Programming Language :: Python :: 3.11
Classifier: Programming Language :: Python :: 3.12
Classifier: Programming Language :: Python :: 3.13
Requires-Dist: asyncio (>=3,<4)
Requires-Dist: colorama (>=0.4,<0.5)
Requires-Dist: fonttools (>=4.49.0,<5.0.0)
Requires-Dist: ipython (>=8,<9)
Requires-Dist: matplotlib (>=3,<4)
Requires-Dist: networkx (>=3,<4)
Requires-Dist: pandas (>=2,<3)
Requires-Dist: pillow (>=10.2.0,<11.0.0)
Requires-Dist: pycryptodome (>=3,<4)
Requires-Dist: tabulate (>=0.9,<0.10)
Requires-Dist: typing-extensions (>=4,<5)
Requires-Dist: uuid (>=1,<2)
Requires-Dist: websocket-client (>=1,<2)
Project-URL: Documentation, https://api.virtualitics.com
